sigma/backends/stix/__init__.py
sigma/backends/stix/stix.py
sigma/pipelines/stix/__init__.py
sigma/pipelines/stix/stix.py
pysigma_backend_stix2-0.2.0.dist-info/LICENSE
pysigma_backend_stix2-0.2.0.dist-info/METADATA
pysigma_backend_stix2-0.2.0.dist-info/WHEEL
pysigma_backend_stix2-0.2.0.dist-info/RECORD
