Metadata-Version: 2.1
Name: pySigma-backend-stix2
Version: 0.2.0
Summary: STIX language backend for pySigma convertor. Forked from https://github.com/barvhaim/pySigma-backend-stix and updated to support latest pySigma versions.
Home-page: https://github.com/slincoln-aiq/pySigma-backend-stix2
License: MIT
Author: Cyber-center of Excellence
Author-email: barha@il.ibm.com
Requires-Python: >=3.8,<4.0
Classifier: License :: OSI Approved :: MIT License
Classifier: Programming Language :: Python :: 3
Classifier: Programming Language :: Python :: 3.8
Classifier: Programming Language :: Python :: 3.9
Classifier: Programming Language :: Python :: 3.10
Classifier: Programming Language :: Python :: 3.11
Classifier: Programming Language :: Python :: 3.12
Requires-Dist: pysigma (>=0.9.5,<0.12.0)
Project-URL: Repository, https://github.com/slincoln-aiq/pySigma-backend-stix2
